bet/Comm.py
bet/__init__.py
bet/sample.py
bet/surrogates.py
bet/util.py
bet/calculateP/__init__.py
bet/calculateP/calculateError.py
bet/calculateP/calculateP.py
bet/calculateP/calculateR.py
bet/calculateP/simpleFunP.py
bet/postProcess/__init__.py
bet/postProcess/compareP.py
bet/postProcess/plotDomains.py
bet/postProcess/plotP.py
bet/postProcess/plotVoronoi.py
bet/postProcess/postTools.py
bet/sampling/LpGeneralizedSamples.py
bet/sampling/__init__.py
bet/sampling/basicSampling.py
bet/sampling/useLUQ.py
bet/sensitivity/__init__.py
bet/sensitivity/chooseQoIs.py
bet/sensitivity/gradients.py
bet-3.0.0.dist-info/COPYING
bet-3.0.0.dist-info/COPYING.LESSER
bet-3.0.0.dist-info/LICENSE.txt
bet-3.0.0.dist-info/METADATA
bet-3.0.0.dist-info/WHEEL
bet-3.0.0.dist-info/top_level.txt
bet-3.0.0.dist-info/RECORD
